[
  {
    "id": "17774",
    "document_name": "MČ-odbor-OMA-záměr-soutěže-NBP-č-775-U-Smaltovny-20G",
    "ext": "pdf",
    "size": "190 KB",
    "url": "https://www.praha7.cz/wp-content/uploads/2018/07/MČ-odbor-OMA-záměr-soutěže-NBP-č-775-U-Smaltovny-20G.pdf"
  },
  {
    "id": "17775",
    "document_name": "MČ-odbor-OMA-záměr-soutěže-NBP-č-775-U-Smaltovny-20G-foto",
    "ext": "pdf",
    "size": "197 KB",
    "url": "https://www.praha7.cz/wp-content/uploads/2018/07/MČ-odbor-OMA-záměr-soutěže-NBP-č-775-U-Smaltovny-20G-foto.pdf"
  },
  {
    "id": "17776",
    "document_name": "MČ-odbor-OMA-záměr-soutěže-NBP-č-775-U-Smaltovny-20G-schéma",
    "ext": "pdf",
    "size": "44 KB",
    "url": "https://www.praha7.cz/wp-content/uploads/2018/07/MČ-odbor-OMA-záměr-soutěže-NBP-č-775-U-Smaltovny-20G-schéma.pdf"
  }
]